<?xml version="1.0" encoding="UTF-8"?>
<vcs-root xmlns:xsi="http://www.w3.org/2001/XMLSchema-instance" uuid="f7623574-ca44-4fa0-9185-36adcb890c1b" type="jetbrains.git" xsi:noNamespaceSchemaLocation="https://www.jetbrains.com/teamcity/schemas/2018.1/project-config.xsd">
  <name>catalogoue_ansible</name>
  <param name="agentCleanFilesPolicy" value="ALL_UNTRACKED" />
  <param name="agentCleanPolicy" value="ON_BRANCH_CHANGE" />
  <param name="authMethod" value="TEAMCITY_SSH_KEY" />
  <param name="branch" value="refs/heads/catalogue" />
  <param name="ignoreKnownHosts" value="true" />
  <param name="submoduleCheckout" value="CHECKOUT" />
  <param name="teamcitySshKey" value="Github" />
  <param name="url" value="git@github.com:Isakova-Svitlana/DeVOps-project.git" />
  <param name="useAlternates" value="true" />
  <param name="username" value="git" />
  <param name="usernameStyle" value="USERID" />
</vcs-root>

